metabot/calendars/google.py
metabot/calendars/test_google.py
metabot.calendars.google-0.2.1.dist-info/METADATA
metabot.calendars.google-0.2.1.dist-info/WHEEL
metabot.calendars.google-0.2.1.dist-info/top_level.txt
metabot.calendars.google-0.2.1.dist-info/RECORD
