Metadata-Version: 2.1
Name: metabot.calendars.google
Version: 0.2.1
Summary: Google Calendar loader for metabot.
Author-email: Daniel Reed <nmlorg@gmail.com>
Project-URL: Homepage, https://github.com/nmlorg/metabot.calendars.google
Project-URL: Issues, https://github.com/nmlorg/metabot.calendars.google/issues
Requires-Python: >=3.8
Requires-Dist: google-api-python-client
Requires-Dist: metabot >=0.3.24
Requires-Dist: oauth2client
Provides-Extra: dev
Requires-Dist: pylint ; extra == 'dev'
Requires-Dist: pytest-cov ; extra == 'dev'
Requires-Dist: pytest ; extra == 'dev'
Requires-Dist: requests-mock ; extra == 'dev'
